tests/__init__.py
tests/test_html.py
tests/test_md.py
tgentity/__init__.py
tgentity/escapers.py
tgentity/mod.py
tgentity/serializers.py
tgentity/types.py
TgEntity_Updated-0.4.0.dist-info/LICENSE
TgEntity_Updated-0.4.0.dist-info/METADATA
TgEntity_Updated-0.4.0.dist-info/WHEEL
TgEntity_Updated-0.4.0.dist-info/top_level.txt
TgEntity_Updated-0.4.0.dist-info/RECORD
