Metadata-Version: 2.1
Name: TgEntity_Updated
Version: 0.4.0
Summary: Telegram entity parser
Home-page: https://github.com/KumaTea/tgentity
Download-URL: https://github.com/KumaTea/tgentity/releases/latest
Author: KumaTea
Author-email: KumaTea <mail@kmtea.eu>
Maintainer-email: KumaTea <mail@kmtea.eu>
License: MIT License
Project-URL: Homepage, https://github.com/KumaTea
Project-URL: Repository, https://github.com/KumaTea/tgentity
Keywords: telegram,entity,entities,parser,html,markdown,v2
Classifier: Development Status :: 3 - Alpha
Classifier: Intended Audience :: Developers
Classifier: License :: OSI Approved :: MIT License
Classifier: Programming Language :: Python
Classifier: Programming Language :: Python :: 3
Classifier: Programming Language :: Python :: 3.6
Classifier: Programming Language :: Python :: 3.7
Classifier: Programming Language :: Python :: 3.8
Classifier: Programming Language :: Python :: 3.9
Classifier: Programming Language :: Python :: 3.10
Classifier: Programming Language :: Python :: 3.11
Classifier: Programming Language :: Python :: 3.12
Classifier: Programming Language :: Python :: Implementation
Classifier: Programming Language :: Python :: Implementation :: CPython
Classifier: Programming Language :: Python :: Implementation :: PyPy
Classifier: Topic :: Communications
Classifier: Topic :: Communications :: Chat
Classifier: Topic :: Software Development :: Libraries
Classifier: Topic :: Software Development :: Libraries :: Python Modules
Requires-Python: >=3.6
License-File: LICENSE
